netplot.py
netplot-0.1.2.dist-info/LICENSE
netplot-0.1.2.dist-info/METADATA
netplot-0.1.2.dist-info/WHEEL
netplot-0.1.2.dist-info/top_level.txt
netplot-0.1.2.dist-info/RECORD
