Metadata-Version: 2.1
Name: netplot
Version: 0.1.2
Summary: Ultralight 3D renderer of neural network architecture for TF/Keras Models
Home-page: https://github.com/Spratiher9/Netplot
Author: Souvik Pratiher
License: UNKNOWN
Platform: UNKNOWN
Classifier: Programming Language :: Python :: 3
Classifier: License :: OSI Approved :: MIT License
Classifier: Operating System :: OS Independent
Requires-Python: >=3.6
License-File: LICENSE
Requires-Dist: cycler (==0.10.0)
Requires-Dist: kiwisolver (==1.3.2)
Requires-Dist: matplotlib (==3.4.3)
Requires-Dist: numpy (==1.21.2)
Requires-Dist: Pillow (==8.3.2)
Requires-Dist: pyparsing (==2.4.7)
Requires-Dist: python-dateutil (==2.8.2)
Requires-Dist: six (==1.16.0)
